Metadata-Version: 2.4
Name: cereja
Version: 2.1.2
Summary: Cereja is a bundle of useful functions that I don't want to rewrite.
Author-email: Joab Leite <leitejoab@gmail.com>
License: Copyright (c) 2019 The Cereja Project
Project-URL: Homepage, https://github.com/cereja-project/cereja
Project-URL: Bug Tracker, https://github.com/cereja-project/cereja/issues/new/choose
Keywords: progress bar,utils,array,pln,file utils
Classifier: Programming Language :: Python :: 3
Classifier: Programming Language :: Python :: 3.6
Classifier: Programming Language :: Python :: 3.7
Classifier: Programming Language :: Python :: 3.8
Classifier: Programming Language :: Python :: 3.9
Classifier: Programming Language :: Python :: 3.10
Classifier: Programming Language :: Python :: 3.11
Classifier: Programming Language :: Python :: 3 :: Only
Classifier: License :: OSI Approved :: MIT License
Classifier: Operating System :: OS Independent
Requires-Python: >=3.6
License-File: LICENSE
Dynamic: license-file
